pip_audit_extra/__init__.py
pip_audit_extra/__main__.py
pip_audit_extra/auditor.py
pip_audit_extra/cli.py
pip_audit_extra/constant.py
pip_audit_extra/generic/__init__.py
pip_audit_extra/generic/path.py
pip_audit_extra/generic/rich/__init__.py
pip_audit_extra/generic/rich/time_elapsed_column.py
pip_audit_extra/iface/__init__.py
pip_audit_extra/iface/osv/__init__.py
pip_audit_extra/iface/osv/router.py
pip_audit_extra/iface/osv/service.py
pip_audit_extra/iface/pip_audit/__init__.py
pip_audit_extra/iface/pip_audit/base.py
pip_audit_extra/iface/pip_audit/dataclass.py
pip_audit_extra/iface/pip_audit/local.py
pip_audit_extra/iface/pip_audit/requirements.py
pip_audit_extra/printer.py
pip_audit_extra/requirement.py
pip_audit_extra/severity.py
pip_audit_extra/vulnerability/__init__.py
pip_audit_extra/vulnerability/cache/__init__.py
pip_audit_extra/vulnerability/cache/cache.py
pip_audit_extra/vulnerability/cache/encoder.py
pip_audit_extra/vulnerability/cache/object_hook.py
pip_audit_extra/vulnerability/cache/type.py
pip_audit_extra/vulnerability/dataclass.py
pip_audit_extra/vulnerability/filter/__init__.py
pip_audit_extra/vulnerability/filter/checker.py
pip_audit_extra/vulnerability/filter/filter.py
pip_audit_extra/vulnerability/filter/filter_option.py
pip_audit_extra/vulnerability/filter/severity.py
pip_audit_extra/vulnerability/print.py
pip_audit_extra/vulnerability/sort.py
pip_audit_extra-1.0.1.dist-info/LICENSE
pip_audit_extra-1.0.1.dist-info/METADATA
pip_audit_extra-1.0.1.dist-info/WHEEL
pip_audit_extra-1.0.1.dist-info/entry_points.txt
pip_audit_extra-1.0.1.dist-info/RECORD
