Metadata-Version: 2.1
Name: pip-audit-extra
Version: 1.0.1
Summary: Extended version of pip-audit
Home-page: https://github.com/Kirill-Lekhov/pip-audit-extra
License: MIT
Keywords: pip-audit,command-line,pip,audit
Author: Kirill_Lekhov
Author-email: kirill.lekhov@mail.ru
Requires-Python: >=3.9,<4.0
Classifier: License :: OSI Approved :: MIT License
Classifier: Programming Language :: Python :: 3
Classifier: Programming Language :: Python :: 3.9
Classifier: Programming Language :: Python :: 3.10
Classifier: Programming Language :: Python :: 3.11
Classifier: Programming Language :: Python :: 3.12
Classifier: Programming Language :: Python :: 3.13
Requires-Dist: pip-audit (>=2.7.3,<3.0.0)
Requires-Dist: rich (>=13.9.4,<14.0.0)
Requires-Dist: urllib3 (>=2.6,<3.0)
Project-URL: Repository, https://github.com/Kirill-Lekhov/pip-audit-extra
